sensitive_info_detector/__init__.py
sensitive_info_detector/detector.py
sensitive_info_detector/patterns.py
tests/__init__.py
detectinfo-1.2.dist-info/METADATA
detectinfo-1.2.dist-info/WHEEL
detectinfo-1.2.dist-info/top_level.txt
detectinfo-1.2.dist-info/RECORD
