Metadata-Version: 2.1
Name: detectinfo
Version: 1.2
Summary: A useful module for detect sensitive information/secrets
Home-page: UNKNOWN
Author: sanket bahir
Author-email: bahirsanket22271@gmail.com
License: UNKNOWN
Platform: UNKNOWN
Requires-Python: >=3.6
Requires-Dist: black
Requires-Dist: pylint
Requires-Dist: pytest
